repcosn/__init__.py
repcosn/main.py
repcosn-1.5.5.dist-info/METADATA
repcosn-1.5.5.dist-info/WHEEL
repcosn-1.5.5.dist-info/top_level.txt
repcosn-1.5.5.dist-info/RECORD
