Metadata-Version: 2.2
Name: repcosn
Version: 1.5.5
Author: Abhidnya Tambe
Dynamic: author
Dynamic: description
Dynamic: description-content-type
